{"width":4096,"imagePath":"armature_tex.png","height":4096,"name":"armature","SubTexture":[{"width":668,"y":1647,"height":599,"name":"LEFT CLAWS","x":1045},{"width":220,"y":2248,"height":190,"name":"LEFT HAND","x":1262},{"width":578,"y":1016,"height":583,"name":"LEFT FOREARM","x":1256},{"width":368,"y":3559,"height":520,"name":"LEFT BICEPS","x":1},{"width":364,"y":3559,"height":458,"name":"LEFT SHOULDER","x":371},{"width":409,"y":1,"height":1013,"name":"LEFT CALF","x":1256},{"width":508,"y":3523,"height":509,"name":"LEFT FOOT","x":1744},{"width":844,"y":2567,"height":729,"name":"LEFT THIGH","x":2411},{"width":665,"y":2567,"height":954,"name":"RIGHT CALF","x":1744},{"width":740,"y":3428,"height":667,"name":"RIGHT FOOT","x":3249},{"width":1253,"y":1,"height":1644,"name":"TORSO","x":1},{"width":687,"y":2567,"height":859,"name":"RIGHT THIGH","x":3257},{"width":914,"y":2567,"height":990,"name":"HEAD 3","x":1},{"width":825,"y":2567,"height":990,"name":"HEAD","x":917},{"width":830,"y":2220,"height":339,"name":"HEAD 4","x":1715},{"width":840,"y":2220,"height":318,"name":"HEAD 2","x":2547},{"width":836,"y":3298,"height":623,"name":"SLINKA","x":2411},{"width":538,"y":1601,"height":617,"name":"RIGHT BICEPS","x":1715},{"width":1042,"y":1647,"height":918,"name":"RIGHT FOREARM","x":1},{"width":215,"y":2248,"height":251,"name":"RIGHT HAND","x":1045},{"width":453,"y":1,"height":709,"name":"RIGHT CLAWS","x":1667},{"width":487,"y":712,"height":613,"name":"RIGHT SHOULDER","x":1836}]}