{"width":2048,"SubTexture":[{"frameWidth":209,"y":1705,"frameHeight":319,"width":156,"frameX":-30,"height":281,"name":"hand alt","frameY":-24,"x":1193},{"width":1161,"y":1,"height":562,"name":"sword","x":1},{"width":299,"y":1539,"height":412,"name":"straznik anim/HEAD","x":601},{"width":236,"y":1140,"height":563,"name":"straznik anim/ARM_2","x":1253},{"width":289,"y":1672,"height":362,"name":"straznik anim/FOREARM_2","x":902},{"width":362,"y":790,"height":695,"name":"straznik anim/LYDKA_1","x":1503},{"width":326,"y":1140,"height":696,"name":"straznik anim/LYDKA_2","x":273},{"width":290,"y":1140,"height":530,"name":"straznik anim/UDO_1","x":961},{"width":353,"y":565,"height":492,"name":"straznik anim/UDO_2","x":273},{"width":358,"y":1059,"height":478,"name":"straznik anim/HIPS","x":601},{"width":360,"y":1,"height":787,"name":"straznik anim/TORSO","x":1503},{"width":343,"y":565,"height":249,"name":"straznik anim/PAS","x":628},{"width":337,"y":1,"height":1137,"name":"straznik anim/SWORD","x":1164},{"width":270,"y":565,"height":911,"name":"straznik anim/POCHWA","x":1},{"width":260,"y":1478,"height":561,"name":"straznik anim/ARM_1","x":1},{"width":166,"y":816,"height":271,"name":"straznik anim/HAND_1","x":961},{"width":224,"y":1487,"height":381,"name":"straznik anim/FOREARM_1","x":1491}],"height":2048,"name":"armature","imagePath":"armature_tex.png"}